setup.py
CentralNotificationSDK/__init__.py
CentralNotificationSDK/notificator.py
notificator.egg-info/PKG-INFO
notificator.egg-info/SOURCES.txt
notificator.egg-info/dependency_links.txt
notificator.egg-info/requires.txt
notificator.egg-info/top_level.txt